pytapas-1.1.5.dist-info/licenses/LICENSE
pytapas-1.1.5.dist-info/licenses/THIRD-PARTY_LICENSES.txt
tapas/LICENSE
tapas/THIRD-PARTY_ACKNOWLEDGEMENTS.txt
tapas/THIRD-PARTY_LICENSES.txt
tapas/__init__.py
tapas/__main__.py
tapas/app.py
tapas/assets/2C_3k_1.svg
tapas/assets/3C_4k_1.svg
tapas/assets/3C_5k_1.svg
tapas/assets/4C_6k_1.svg
tapas/assets/SVD.svg
tapas/assets/about.svg
tapas/assets/acknowledgements.svg
tapas/assets/brand-github.svg
tapas/assets/brand-youtube.svg
tapas/assets/code.svg
tapas/assets/combine.svg
tapas/assets/doc.svg
tapas/assets/file-settings.svg
tapas/assets/global_fit.svg
tapas/assets/icon.icns
tapas/assets/icon.ico
tapas/assets/icon.svg
tapas/assets/import.svg
tapas/assets/license.svg
tapas/assets/local_fit.svg
tapas/assets/mpl_style.svg
tapas/assets/new_project.svg
tapas/assets/open_config.svg
tapas/assets/open_project.svg
tapas/assets/parallel.svg
tapas/assets/preprocess.svg
tapas/assets/save_as.svg
tapas/assets/save_config.svg
tapas/assets/save_config_as.svg
tapas/assets/save_project.svg
tapas/assets/sequential.svg
tapas/assets/splash.png
tapas/assets/third_party_license.svg
tapas/assets/visualization.svg
tapas/assets/x.svg
tapas/configurations/__init__.py
tapas/configurations/default_gui_config.json
tapas/configurations/default_style.mplstyle
tapas/configurations/exceptions.py
tapas/configurations/gui_styles.css
tapas/configurations/log_config.ini
tapas/configurations/messages.py
tapas/configurations/fonts/OFL.txt
tapas/configurations/fonts/Roboto_Condensed-Bold.ttf
tapas/configurations/fonts/Roboto_Condensed-BoldItalic.ttf
tapas/configurations/fonts/Roboto_Condensed-ExtraLight.ttf
tapas/configurations/fonts/Roboto_Condensed-ExtraLightItalic.ttf
tapas/configurations/fonts/Roboto_Condensed-Italic.ttf
tapas/configurations/fonts/Roboto_Condensed-Light.ttf
tapas/configurations/fonts/Roboto_Condensed-LightItalic.ttf
tapas/configurations/fonts/Roboto_Condensed-Medium.ttf
tapas/configurations/fonts/Roboto_Condensed-MediumItalic.ttf
tapas/configurations/fonts/Roboto_Condensed-Regular.ttf
tapas/configurations/fonts/Roboto_Condensed-SemiBold.ttf
pytapas-1.1.5.dist-info/METADATA
pytapas-1.1.5.dist-info/WHEEL
pytapas-1.1.5.dist-info/entry_points.txt
pytapas-1.1.5.dist-info/top_level.txt
pytapas-1.1.5.dist-info/RECORD
