Metadata-Version: 2.4
Name: pytapas
Version: 1.1.5
Summary: Transient Absorption Processing & Analysis Software
Author: Philipp Frech
License-Expression: GPL-3.0-or-later
Classifier: Programming Language :: Python :: 3.11
Classifier: Operating System :: OS Independent
Requires-Python: <3.12,>=3.11
License-File: LICENSE
License-File: THIRD-PARTY_LICENSES.txt
Requires-Dist: arviz>=0.21.0
Requires-Dist: corner>=2.2.3
Requires-Dist: emcee>=3.1.6
Requires-Dist: h5py>=3.13.0
Requires-Dist: jax[cpu]<0.6.0,>=0.4.30
Requires-Dist: jax[cpu]<0.5.0; sys_platform == "darwin" and platform_machine == "x86_64"
Requires-Dist: jaxlib<0.6.0,>=0.4.0
Requires-Dist: lmfit>=1.3.3
Requires-Dist: matplotlib>=3.10
Requires-Dist: numpy>=2.2.4
Requires-Dist: pyqt6>=6.9
Requires-Dist: pyqtconfig>=0.9.2
Requires-Dist: scipy>=1.15.2
Provides-Extra: dev
Requires-Dist: build>=1.2.2; extra == "dev"
Provides-Extra: bundle
Requires-Dist: pyinstaller>=6.13; extra == "bundle"
Requires-Dist: pyinstaller-hooks-contrib>=2025.3; extra == "bundle"
Provides-Extra: docs
Requires-Dist: sphinx>=5.0; extra == "docs"
Requires-Dist: sphinx-book-theme; extra == "docs"
Requires-Dist: sphinx-tabs; extra == "docs"
Dynamic: license-file
